ml_cli_azureml_pipeline/__init__.py
ml_cli_azureml_pipeline/environment.py
ml_cli_azureml_pipeline/run.py
ml_cli_azureml_pipeline/modules/__init__.py
ml_cli_azureml_pipeline/modules/extraction/__init__.py
ml_cli_azureml_pipeline/modules/extraction/extraction.py
ml_cli_azureml_pipeline/modules/extraction/extraction_step.py
ml_cli_azureml_pipeline/modules/extraction/ml_cli.py
ml_cli_azureml_pipeline/modules/ingestion_chunk/__init__.py
ml_cli_azureml_pipeline/modules/ingestion_chunk/chunk_files.py
ml_cli_azureml_pipeline/modules/ingestion_chunk/data_ingestion.py
ml_cli_azureml_pipeline/modules/ingestion_chunk/data_ingestion_step.py
ml_cli_azureml_pipeline/modules/ingestion_chunk/tests/__init__.py
ml_cli_azureml_pipeline/modules/ingestion_chunk/tests/test_chunk_files.py
ml_cli_azureml_pipeline/modules/save/__init__.py
ml_cli_azureml_pipeline/modules/save/aggregate_output.py
ml_cli_azureml_pipeline/modules/save/save.py
ml_cli_azureml_pipeline/modules/save/save_step.py
ml_cli_azureml_pipeline/modules/save/tests/__init__.py
ml_cli_azureml_pipeline/modules/save/tests/test_aggregate_output.py
ml_cli_azureml_pipeline/pipelines/__init__.py
ml_cli_azureml_pipeline/pipelines/train_pipeline.py
ml_cli_azureml_pipeline-0.0.41.dist-info/LICENSE
ml_cli_azureml_pipeline-0.0.41.dist-info/METADATA
ml_cli_azureml_pipeline-0.0.41.dist-info/WHEEL
ml_cli_azureml_pipeline-0.0.41.dist-info/top_level.txt
ml_cli_azureml_pipeline-0.0.41.dist-info/RECORD
